machine_learning_py-3.5.8.dist-info/METADATA
machine_learning_py-3.5.8.dist-info/RECORD
machine_learning_py-3.5.8.dist-info/WHEEL
machine_learning_py-3.5.8.dist-info/top_level.txt
mlpy/__init__.py
mlpy/adatron.cpython-36m-darwin.so
mlpy/canberra.cpython-36m-darwin.so
mlpy/crossval.py
mlpy/da.py
mlpy/dimred.py
mlpy/dtw.cpython-36m-darwin.so
mlpy/elasticnet.py
mlpy/findpeaks.cpython-36m-darwin.so
mlpy/golub.py
mlpy/gsl.cpython-36m-darwin.so
mlpy/irelief.py
mlpy/kernel.cpython-36m-darwin.so
mlpy/kernel_class.py
mlpy/kmeans.cpython-36m-darwin.so
mlpy/lars.py
mlpy/lcs.cpython-36m-darwin.so
mlpy/liblinear.cpython-36m-darwin.so
mlpy/libml.cpython-36m-darwin.so
mlpy/libsvm.cpython-36m-darwin.so
mlpy/metrics.py
mlpy/ols.py
mlpy/parzen.py
mlpy/perceptron.py
mlpy/pls.py
mlpy/rfe.py
mlpy/ridge.py
mlpy/stats.py
mlpy/version.py
mlpy/bordacount/__init__.py
mlpy/bordacount/borda.py
mlpy/bordacount/cborda.cpython-36m-darwin.so
mlpy/fastcluster/__init__.py
mlpy/fastcluster/_fastcluster.cpython-36m-darwin.so
mlpy/fastcluster/fastcluster.py
mlpy/fastcluster/fasthc.py
mlpy/hcluster/__init__.py
mlpy/hcluster/chc.cpython-36m-darwin.so
mlpy/hcluster/hc.py
mlpy/wavelet/__init__.py
mlpy/wavelet/_dwt.cpython-36m-darwin.so
mlpy/wavelet/_uwt.cpython-36m-darwin.so
mlpy/wavelet/continuous.py
mlpy/wavelet/padding.py
mlpy/wavelet/uwt_align.py
